{
    "name": "holistic",
    "description": "A domain and process modeling system for building Node.js/HTML5 SaaS and PaaS products dynamically from JSON data + remixable plug-ins written in JavaScript.",
    "version": "0.0.54",
    "codename": "citrine",
    "author": "Encapsule",
    "copyright": {
        "holder": "Christopher D. Russell",
        "year": 2021
    },
    "contributors": [
        {
            "name": "Christopher D. Russell",
            "email": "cdr@encapsule.io",
            "url": "https://github.com/ChrisRus"
        }
    ],
    "license": "MIT",
    "buildID": "xmwVqOhrSPyh6EaAp73BiA",
    "buildSource": "eeff2492346710e7e50b165a7a2ee328c098bd54",
    "buildTime": 1614363930,
    "buildDateISO": "2021-02-26T18:25:30.000Z"
}
