{
    "name": "holistic",
    "description": "A plug-in filter extensible, JSON configurable framework for building full-stack Node.js/HTML5 applications.",
    "version": "0.0.12",
    "codename": "skyhook",
    "author": "Encapsule",
    "copyright": {
        "holder": "Christopher D. Russell",
        "year": 2019
    },
    "contributors": [
        {
            "name": "Christopher D. Russell",
            "email": "cdr@encapsule.io",
            "url": "http://chrisrussell.net"
        }
    ],
    "license": "MIT",
    "buildID": "zrFmoGIZTqqEE8kf72SSVw",
    "buildSource": "991aa75b3becb15dd0e08a2b47cd8f06a1ea4498",
    "buildTime": 1557187079,
    "buildDateISO": "2019-05-06T23:57:59.000Z"
}
