{
    "name": "holistic",
    "description": "A plug-in filter extensible, JSON configurable framework for building full-stack Node.js/HTML5 applications.",
    "version": "0.0.6",
    "codename": "slapshot",
    "author": "Encapsule",
    "copyright": {
        "holder": "Christopher D. Russell",
        "year": 2019
    },
    "contributors": [
        {
            "name": "Christopher D. Russell",
            "email": "cdr@encapsule.io",
            "url": "http://chrisrussell.net"
        }
    ],
    "license": "MIT",
    "buildID": "g_4bTEoISpWVepU9KkLjAw",
    "buildSource": "272a169995ca2b9578b1d5e7e007369d0318d5fe",
    "buildTime": 1550619071,
    "buildDateISO": "2019-02-19T23:31:11.000Z"
}
