{
    "name": "holistic",
    "description": "A plug-in filter extensible, JSON configurable framework for building full-stack Node.js/HTML5 applications.",
    "version": "0.0.25",
    "codename": "stryker",
    "author": "Encapsule",
    "copyright": {
        "holder": "Christopher D. Russell",
        "year": 2019
    },
    "contributors": [
        {
            "name": "Christopher D. Russell",
            "email": "cdr@encapsule.io",
            "url": "https://github.com/ChrisRus"
        }
    ],
    "license": "MIT",
    "buildID": "qPeHzu9AQyiDzc5GkI74sw",
    "buildSource": "cc9fba4faf3ea6aeb6e69124f0e52009dba81b92",
    "buildTime": 1573957695,
    "buildDateISO": "2019-11-17T02:28:15.000Z"
}
