{
    "name": "holistic",
    "description": "A plug-in filter extensible, JSON configurable framework for building full-stack Node.js/HTML5 applications.",
    "version": "0.0.14",
    "codename": "olecoulee",
    "author": "Encapsule",
    "copyright": {
        "holder": "Christopher D. Russell",
        "year": 2019
    },
    "contributors": [
        {
            "name": "Christopher D. Russell",
            "email": "cdr@encapsule.io",
            "url": "http://chrisrussell.net"
        }
    ],
    "license": "MIT",
    "buildID": "QxiioRt1RASB3r_Y_1VbOw",
    "buildSource": "bc711032d627bbac8d16b845b833b75de3cd4dcd",
    "buildTime": 1559858041,
    "buildDateISO": "2019-06-06T21:54:01.000Z"
}
