{
    "name": "holistic",
    "description": "A plug-in filter extensible, JSON configurable framework for building full-stack Node.js/HTML5 applications.",
    "version": "0.0.7",
    "codename": "rexford",
    "author": "Encapsule",
    "copyright": {
        "holder": "Christopher D. Russell",
        "year": 2019
    },
    "contributors": [
        {
            "name": "Christopher D. Russell",
            "email": "cdr@encapsule.io",
            "url": "http://chrisrussell.net"
        }
    ],
    "license": "MIT",
    "buildID": "aU3NdnICS0q8VyZNZFfhgA",
    "buildSource": "189a07c2b94295828966aab9cbc0c277ee7fd196",
    "buildTime": 1550957034,
    "buildDateISO": "2019-02-23T21:23:54.000Z"
}
