{
    "name": "holistic",
    "description": "A plug-in filter extensible, JSON configurable framework for building full-stack Node.js/HTML5 applications.",
    "version": "0.0.33",
    "codename": "quatsino",
    "author": "Encapsule",
    "copyright": {
        "holder": "Christopher D. Russell",
        "year": 2020
    },
    "contributors": [
        {
            "name": "Christopher D. Russell",
            "email": "cdr@encapsule.io",
            "url": "https://github.com/ChrisRus"
        }
    ],
    "license": "MIT",
    "buildID": "U3C5O8hGTN6mRje5FZQ0Dw",
    "buildSource": "032cf574c27d38073122f7652a88ebd1c3081ac3",
    "buildTime": 1579320101,
    "buildDateISO": "2020-01-18T04:01:41.000Z"
}
